setup.py
bin/stashcli
stashcli/__init__.py
stashcli/config.py
stashcli/errors.py
stashcli/hipchat.py
stashcli/pullrequest.py
stashcli/template.py
stashcli.egg-info/PKG-INFO
stashcli.egg-info/SOURCES.txt
stashcli.egg-info/dependency_links.txt
stashcli.egg-info/requires.txt
stashcli.egg-info/top_level.txt