Metadata-Version: 1.0
Name: stashcli
Version: 1.0.0
Summary: Make pull-requests to Stash repos from the CLI, and notify the ream via Hipchat.
Home-page: https://github.com/purinda/stash-cli
Author: Purinda Gunasekara
Author-email: purinda@gmail.com
License: LICENSE.md
Platform: UNKNOWN
